sendgrid_ovh/__init__.py
sendgrid_ovh/__main__.py
sendgrid_ovh/__version__.py
sendgrid_ovh/lib/OVHClientFactory.py
sendgrid_ovh/lib/OVHZone.py
sendgrid_ovh/lib/OnePasswordCli.py
sendgrid_ovh/lib/Output.py
sendgrid_ovh/lib/SendGridClientFactory.py
sendgrid_ovh/lib/SendGridWhiteLabel.py
sendgrid_ovh/lib/__init__.py
sendgrid_ovh/sendgrid/__init__.py
sendgrid_ovh/sendgrid/sendgrid.py
sendgrid_ovh/zone/__init__.py
sendgrid_ovh/zone/zone.py
sendgrid_ovh-0.0.6.dist-info/METADATA
sendgrid_ovh-0.0.6.dist-info/WHEEL
sendgrid_ovh-0.0.6.dist-info/entry_points.txt
sendgrid_ovh-0.0.6.dist-info/top_level.txt
sendgrid_ovh-0.0.6.dist-info/RECORD
