Metadata-Version: 2.1
Name: sendgrid-ovh
Version: 0.0.6
Summary: Tool to easily manipulate OVH Zone and domain authenticate sendgrid automatically
Home-page: https://github.com/mickaelperrin/sendgrid-ovh
Author: Mickaël Perrin
Author-email: dev@mickaelperrin.fr
License: GPLv3
Keywords: OVH DNS zone sendgrid cli domain authentication
Classifier: License :: OSI Approved :: GNU General Public License v3 or later (GPLv3+)
Classifier: Development Status :: 4 - Beta
Classifier: Environment :: Console
Classifier: Intended Audience :: Information Technology
Classifier: Natural Language :: French
Classifier: Topic :: Utilities
Classifier: Programming Language :: Python
Classifier: Programming Language :: Python :: 3
Classifier: Programming Language :: Python :: 3.7
Classifier: Programming Language :: Python :: Implementation :: CPython
Classifier: Programming Language :: Python :: Implementation :: PyPy
Requires-Python: >=3.7.0
Requires-Dist: sendgrid
Requires-Dist: click
Requires-Dist: ovh
Requires-Dist: rich
Requires-Dist: tldextract
